[
    {
       "menuCode":1,
       "menuName":"페트병",
       "categoryName":"플라스틱",
       "isOrderable":true,
       "detail": {
           "description": "페트병 용기에 든 내용물은 깨끗이 비우고, 부착상표와 뚜껑 등 다른 재질로 된 부분은 제거",
           "image": "/recycleImages/1.png"
       }
    },
    {
       "menuCode":2,
       "menuName":"플라스틱 용기",
       "categoryName":"플라스틱",
       "isOrderable":true,
       "detail": {
           "description": "태안 바다에서 갓 잡아올린 싱싱한 우럭을 이용한 상큼한 스무디",
           "image": "/recycleImages/2.png"
       }
    },
    {
       "menuCode":3,
       "menuName":"알약포장재",
       "categoryName":"플라스틱",
       "isOrderable":true,
       "detail": {
           "description": "목포 밤바다를 누비는 생갈치를 이용한 고단백 쉐이크 음료",
           "image": "/recycleImages/3.png"
       }
    },
    {
       "menuCode":4,
       "menuName":"카세프 테이프",
       "categoryName":"플라스틱",
       "isOrderable":true,
       "detail": {
           "description": "향균작용이 뛰어난 생마늘과 혈행개선에 도움을 주는 미역을 이용한 건강한 디저트 파르페",
           "image": "/recycleImages/4.png"
       }
    },
    {
       "menuCode":5,
       "menuName":"기타 테이프",
       "categoryName":"플라스틱",
       "isOrderable":true,
       "detail": {
           "description": "향균작용이 뛰어난 생마늘과 혈행개선에 도움을 주는 미역을 이용한 건강한 디저트 파르페",
           "image": "/recycleImages/4.png"
       }
    },
    {
       "menuCode":6,
       "menuName":"기타 테이프",
       "categoryName":"플라스틱",
       "isOrderable":true,
       "detail": {
           "description": "향균작용이 뛰어난 생마늘과 혈행개선에 도움을 주는 미역을 이용한 건강한 디저트 파르페",
           "image": "/recycleImages/4.png"
       }
    },
    {
       "menuCode":7,
       "menuName":"기타 테이프",
       "categoryName":"일반",
       "isOrderable":true,
       "detail": {
           "description": "향균작용이 뛰어난 생마늘과 혈행개선에 도움을 주는 미역을 이용한 건강한 디저트 파르페",
           "image": "/recycleImages/4.png"
       }
    },
    {
       "menuCode":8,
       "menuName":"기타 테이프",
       "categoryName":"일반",
       "isOrderable":true,
       "detail": {
           "description": "향균작용이 뛰어난 생마늘과 혈행개선에 도움을 주는 미역을 이용한 건강한 디저트 파르페",
           "image": "/recycleImages/4.png"
       }
    },
    {
       "menuCode":9,
       "menuName":"기타 테이프",
       "categoryName":"일반",
       "isOrderable":true,
       "detail": {
           "description": "향균작용이 뛰어난 생마늘과 혈행개선에 도움을 주는 미역을 이용한 건강한 디저트 파르페",
           "image": "/recycleImages/4.png"
       }
    },
    {
       "menuCode":10,
       "menuName":"기타 테이프",
       "categoryName":"일반",
       "isOrderable":true,
       "detail": {
           "description": "향균작용이 뛰어난 생마늘과 혈행개선에 도움을 주는 미역을 이용한 건강한 디저트 파르페",
           "image": "/recycleImages/4.png"
       }
    },
    {
       "menuCode":11,
       "menuName":"기타 테이프",
       "categoryName":"일반",
       "isOrderable":true,
       "detail": {
           "description": "향균작용이 뛰어난 생마늘과 혈행개선에 도움을 주는 미역을 이용한 건강한 디저트 파르페",
           "image": "/recycleImages/4.png"
       }
    },
    {
       "menuCode":12,
       "menuName":"기타 테이프",
       "categoryName":"일반",
       "isOrderable":true,
       "detail": {
           "description": "향균작용이 뛰어난 생마늘과 혈행개선에 도움을 주는 미역을 이용한 건강한 디저트 파르페",
           "image": "/recycleImages/4.png"
       }
    },
    {
       "menuCode":13,
       "menuName":"기타 테이프",
       "categoryName":"종이",
       "isOrderable":true,
       "detail": {
           "description": "향균작용이 뛰어난 생마늘과 혈행개선에 도움을 주는 미역을 이용한 건강한 디저트 파르페",
           "image": "/recycleImages/4.png"
       }
    },
    {
       "menuCode":14,
       "menuName":"기타 테이프",
       "categoryName":"종이",
       "isOrderable":true,
       "detail": {
           "description": "향균작용이 뛰어난 생마늘과 혈행개선에 도움을 주는 미역을 이용한 건강한 디저트 파르페",
           "image": "/recycleImages/4.png"
       }
    },
    {
       "menuCode":15,
       "menuName":"기타 테이프",
       "categoryName":"종이",
       "isOrderable":true,
       "detail": {
           "description": "향균작용이 뛰어난 생마늘과 혈행개선에 도움을 주는 미역을 이용한 건강한 디저트 파르페",
           "image": "/recycleImages/4.png"
       }
    },
    {
       "menuCode":16,
       "menuName":"기타 테이프",
       "categoryName":"종이",
       "isOrderable":true,
       "detail": {
           "description": "향균작용이 뛰어난 생마늘과 혈행개선에 도움을 주는 미역을 이용한 건강한 디저트 파르페",
           "image": "/recycleImages/4.png"
       }
    },
    {
       "menuCode":17,
       "menuName":"기타 테이프",
       "categoryName":"종이",
       "isOrderable":true,
       "detail": {
           "description": "향균작용이 뛰어난 생마늘과 혈행개선에 도움을 주는 미역을 이용한 건강한 디저트 파르페",
           "image": "/recycleImages/4.png"
       }
    },
    {
       "menuCode":18,
       "menuName":"기타 테이프",
       "categoryName":"종이",
       "isOrderable":true,
       "detail": {
           "description": "향균작용이 뛰어난 생마늘과 혈행개선에 도움을 주는 미역을 이용한 건강한 디저트 파르페",
           "image": "/recycleImages/4.png"
       }
    },
    {
       "menuCode":19,
       "menuName":"기타 테이프",
       "categoryName":"음식물",
       "isOrderable":true,
       "detail": {
           "description": "향균작용이 뛰어난 생마늘과 혈행개선에 도움을 주는 미역을 이용한 건강한 디저트 파르페",
           "image": "/recycleImages/4.png"
       }
    },
    {
       "menuCode":20,
       "menuName":"기타 테이프",
       "categoryName":"음식물",
       "isOrderable":true,
       "detail": {
           "description": "향균작용이 뛰어난 생마늘과 혈행개선에 도움을 주는 미역을 이용한 건강한 디저트 파르페",
           "image": "/recycleImages/4.png"
       }
    },
    {
       "menuCode":21,
       "menuName":"기타 테이프",
       "categoryName":"음식물",
       "isOrderable":true,
       "detail": {
           "description": "향균작용이 뛰어난 생마늘과 혈행개선에 도움을 주는 미역을 이용한 건강한 디저트 파르페",
           "image": "/recycleImages/4.png"
       }
    },
    {
       "menuCode":22,
       "menuName":"기타 테이프",
       "categoryName":"음식물",
       "isOrderable":true,
       "detail": {
           "description": "향균작용이 뛰어난 생마늘과 혈행개선에 도움을 주는 미역을 이용한 건강한 디저트 파르페",
           "image": "/recycleImages/4.png"
       }
    },
    {
       "menuCode":23,
       "menuName":"기타 테이프",
       "categoryName":"음식물",
       "isOrderable":true,
       "detail": {
           "description": "향균작용이 뛰어난 생마늘과 혈행개선에 도움을 주는 미역을 이용한 건강한 디저트 파르페",
           "image": "/recycleImages/4.png"
       }
    },
    {
       "menuCode":24,
       "menuName":"기타 테이프",
       "categoryName":"음식물",
       "isOrderable":true,
       "detail": {
           "description": "향균작용이 뛰어난 생마늘과 혈행개선에 도움을 주는 미역을 이용한 건강한 디저트 파르페",
           "image": "/recycleImages/4.png"
       }
    },
    {
       "menuCode":25,
       "menuName":"기타 테이프",
       "categoryName":"기타",
       "isOrderable":true,
       "detail": {
           "description": "향균작용이 뛰어난 생마늘과 혈행개선에 도움을 주는 미역을 이용한 건강한 디저트 파르페",
           "image": "/recycleImages/4.png"
       }
    },
    {
       "menuCode":26,
       "menuName":"기타 테이프",
       "categoryName":"기타",
       "isOrderable":true,
       "detail": {
           "description": "향균작용이 뛰어난 생마늘과 혈행개선에 도움을 주는 미역을 이용한 건강한 디저트 파르페",
           "image": "/recycleImages/4.png"
       }
    },
    {
       "menuCode":27,
       "menuName":"기타 테이프",
       "categoryName":"기타",
       "isOrderable":true,
       "detail": {
           "description": "향균작용이 뛰어난 생마늘과 혈행개선에 도움을 주는 미역을 이용한 건강한 디저트 파르페",
           "image": "/recycleImages/4.png"
       }
    },
    {
       "menuCode":28,
       "menuName":"기타 테이프",
       "categoryName":"기타",
       "isOrderable":true,
       "detail": {
           "description": "향균작용이 뛰어난 생마늘과 혈행개선에 도움을 주는 미역을 이용한 건강한 디저트 파르페",
           "image": "/recycleImages/4.png"
       }
    },
    {
       "menuCode":29,
       "menuName":"기타 테이프",
       "categoryName":"기타",
       "isOrderable":true,
       "detail": {
           "description": "향균작용이 뛰어난 생마늘과 혈행개선에 도움을 주는 미역을 이용한 건강한 디저트 파르페",
           "image": "/recycleImages/4.png"
       }
    },
    {
       "menuCode":30,
       "menuName":"기타 테이프",
       "categoryName":"기타",
       "isOrderable":true,
       "detail": {
           "description": "향균작용이 뛰어난 생마늘과 혈행개선에 도움을 주는 미역을 이용한 건강한 디저트 파르페",
           "image": "/recycleImages/4.png"
       }
    }
 
 ]